finjet/__init__.py
finjet/container.py
finjet/dependency.py
finjet/functional.py
finjet/injecter.py
finjet-0.1.3.dist-info/WHEEL
finjet-0.1.3.dist-info/METADATA
finjet-0.1.3.dist-info/RECORD
