Metadata-Version: 2.1
Name: finjet
Version: 0.1.3
Summary: Dependency injection like FastAPI.
License: Apache2.0
Keywords: Dependency injection,DI,Inversion of Control,IoC,Factory,Singleton,Design patterns
Author: elda27
Author-email: kaz.birdstick@gmail.com
Requires-Python: >=3.8,<4.0
Classifier: License :: Other/Proprietary License
Classifier: Programming Language :: Python :: 3
Classifier: Programming Language :: Python :: 3.10
Classifier: Programming Language :: Python :: 3.6
Classifier: Programming Language :: Python :: 3.7
Classifier: Programming Language :: Python :: 3.8
Classifier: Programming Language :: Python :: 3.9
Classifier: Topic :: Software Development
Classifier: Topic :: Software Development :: Libraries
Classifier: Topic :: Software Development :: Libraries :: Python Modules
Requires-Dist: pydantic
